{
  "version": "7",
  "dialect": "sqlite",
  "entries": [
    {
      "idx": 0,
      "version": "6",
      "when": 1758278136565,
      "tag": "0000_cuddly_punisher",
      "breakpoints": true
    },
    {
      "idx": 1,
      "version": "6",
      "when": 1758307038527,
      "tag": "0001_rich_centennial",
      "breakpoints": true
    },
    {
      "idx": 2,
      "version": "6",
      "when": 1759995206460,
      "tag": "0002_rapid_kang",
      "breakpoints": true
    },
    {
      "idx": 3,
      "version": "6",
      "when": 1762519320267,
      "tag": "0003_reflective_jack_murdock",
      "breakpoints": true
    },
    {
      "idx": 4,
      "version": "6",
      "when": 1763038505613,
      "tag": "0004_add_vehicle_inventory",
      "breakpoints": true
    },
    {
      "idx": 5,
      "version": "6",
      "when": 1765354787388,
      "tag": "0005_huge_hellion",
      "breakpoints": true
    }
  ]
}